{"is_source_file": true, "format": "JavaScript (React)", "description": "React component App implementing theme toggle functionality with state management and theme application via useEffect.", "external_files": ["./logo.svg", "./App.css"], "external_methods": ["React.useState", "React.useEffect"], "published": ["App"], "classes": [], "methods": [{"name": "App()", "description": "React functional component that renders a toggle theme button, logo, instructional text, and link.", "scope": "", "scopeKind": ""}, {"name": "toggleTheme", "description": "Function to toggle between 'light' and 'dark' themes upon button click."}], "calls": ["React.useState", "React.useEffect", "document.documentElement.setAttribute", "setTheme", "prevTheme => prevTheme === 'light' ? 'dark' : 'light'", "document.querySelector", "console.log"], "search-terms": ["React theme toggle", "useState hook", "useEffect hook", "App.js React component", "Theme switch button"], "state": 2, "file_id": 6, "knowledge_revision": 25, "git_revision": "fd07941ce1a51b5d3b4309cf7d9ba6f28d0d25e9", "ctags": [{"_type": "tag", "name": "App", "path": "/home/kavia/workspace/code-generation/interactive-tic-tac-toe-50793-50804/tic_tac_toe_frontend/src/App.js", "pattern": "/^function App() {$/", "language": "JavaScript", "kind": "function", "signature": "()"}, {"_type": "tag", "name": "Switch to ${theme === 'light' ? 'dark' : 'light'} mode", "path": "/home/kavia/workspace/code-generation/interactive-tic-tac-toe-50793-50804/tic_tac_toe_frontend/src/App.js", "pattern": "/^          aria-label={`Switch to ${theme === 'light' ? 'dark' : 'light'} mode`}$/", "language": "JavaScript", "kind": "field", "scope": "App.aria", "scopeKind": "class"}, {"_type": "tag", "name": "toggleTheme", "path": "/home/kavia/workspace/code-generation/interactive-tic-tac-toe-50793-50804/tic_tac_toe_frontend/src/App.js", "pattern": "/^          onClick={toggleTheme}$/", "language": "JavaScript", "kind": "field", "scope": "App.onClick", "scopeKind": "class"}], "hash": "b55dd9e6a018e59207d8e277dffd9e11", "format-version": 4, "code-base-name": "tic_tac_toe_frontend", "filename": "tic_tac_toe_frontend/src/App.js", "fields": [{"name": "aria-label={`Switch to ${theme === 'light' ? 'dark' : 'light'} mode`}", "scope": "App.aria", "scopeKind": "class", "description": "unavailable"}, {"name": "onClick={toggleTheme}", "scope": "App.onClick", "scopeKind": "class", "description": "unavailable"}], "revision_history": [{"25": "fd07941ce1a51b5d3b4309cf7d9ba6f28d0d25e9"}]}